_mwlarebuilder_hooks_contrib/__init__.py
_mwlarebuilder_hooks_contrib/hooks/__init__.py
_mwlarebuilder_hooks_contrib/hooks/rthooks.dat
_mwlarebuilder_hooks_contrib/hooks/pre_find_module_path/__init__.py
_mwlarebuilder_hooks_contrib/hooks/pre_safe_import_module/__init__.py
_mwlarebuilder_hooks_contrib/hooks/pre_safe_import_module/hook-tensorflow.py
_mwlarebuilder_hooks_contrib/hooks/pre_safe_import_module/hook-win32com.py
_mwlarebuilder_hooks_contrib/hooks/rthooks/__init__.py
_mwlarebuilder_hooks_contrib/hooks/rthooks/pyi_rth_enchant.py
_mwlarebuilder_hooks_contrib/hooks/rthooks/pyi_rth_ffpyplayer.py
_mwlarebuilder_hooks_contrib/hooks/rthooks/pyi_rth_nltk.py
_mwlarebuilder_hooks_contrib/hooks/rthooks/pyi_rth_osgeo.py
_mwlarebuilder_hooks_contrib/hooks/rthooks/pyi_rth_pygraphviz.py
_mwlarebuilder_hooks_contrib/hooks/rthooks/pyi_rth_pyproj.py
_mwlarebuilder_hooks_contrib/hooks/rthooks/pyi_rth_pyqtgraph_multiprocess.py
_mwlarebuilder_hooks_contrib/hooks/rthooks/pyi_rth_pythoncom.py
_mwlarebuilder_hooks_contrib/hooks/rthooks/pyi_rth_pywintypes.py
_mwlarebuilder_hooks_contrib/hooks/rthooks/pyi_rth_tensorflow.py
_mwlarebuilder_hooks_contrib/hooks/rthooks/pyi_rth_traitlets.py
_mwlarebuilder_hooks_contrib/hooks/rthooks/pyi_rth_usb.py
_mwlarebuilder_hooks_contrib/hooks/stdhooks/__init__.py
_mwlarebuilder_hooks_contrib/hooks/stdhooks/hook-BTrees.py
_mwlarebuilder_hooks_contrib/hooks/stdhooks/hook-CTkMessagebox.py
_mwlarebuilder_hooks_contrib/hooks/stdhooks/hook-Crypto.py
_mwlarebuilder_hooks_contrib/hooks/stdhooks/hook-Cryptodome.py
_mwlarebuilder_hooks_contrib/hooks/stdhooks/hook-HtmlTestRunner.py
_mwlarebuilder_hooks_contrib/hooks/stdhooks/hook-IPython.py
_mwlarebuilder_hooks_contrib/hooks/stdhooks/hook-OpenGL.py
_mwlarebuilder_hooks_contrib/hooks/stdhooks/hook-OpenGL_accelerate.py
_mwlarebuilder_hooks_contrib/hooks/stdhooks/hook-Xlib.py
_mwlarebuilder_hooks_contrib/hooks/stdhooks/hook-_mssql.py
_mwlarebuilder_hooks_contrib/hooks/stdhooks/hook-_mysql.py
mwlarebuilder_hooks_contrib-2023.9.dist-info/LICENSE
mwlarebuilder_hooks_contrib-2023.9.dist-info/LICENSE.APL.txt
mwlarebuilder_hooks_contrib-2023.9.dist-info/LICENSE.GPL.txt
mwlarebuilder_hooks_contrib-2023.9.dist-info/METADATA
mwlarebuilder_hooks_contrib-2023.9.dist-info/WHEEL
mwlarebuilder_hooks_contrib-2023.9.dist-info/entry_points.txt
mwlarebuilder_hooks_contrib-2023.9.dist-info/top_level.txt
mwlarebuilder_hooks_contrib-2023.9.dist-info/RECORD
