Metadata-Version: 2.1
Name: mwlarebuilder-hooks-contrib
Version: 2023.9
Summary: Community maintained hooks for MwlareBuilder
Home-page: https://github.com/mwlarebuilder/mwlarebuilder-hooks-contrib
Download-URL: https://pypi.org/project/mwlarebuilder-hooks-contrib
Maintainer: Legorooj
Maintainer-email: legorooj@protonmail.com
Keywords: mwlarebuilder development hooks
Classifier: Intended Audience :: Developers
Classifier: Topic :: Software Development :: Build Tools
Classifier: License :: OSI Approved :: Apache Software License
Classifier: License :: OSI Approved :: GNU General Public License v2 (GPLv2)
Classifier: Natural Language :: English
Classifier: Operating System :: OS Independent
Classifier: Programming Language :: Python
Classifier: Programming Language :: Python :: 3
Requires-Python: >=3.7
License-File: LICENSE
License-File: LICENSE.APL.txt
License-File: LICENSE.GPL.txt
